{
  "products": [
    {
      "id": 1,
      "title": "black shirt",
      "category" : "Men Clothing",
      "cost": "20"
    },
    {
      "id": 2,
      "title": "red shirt",
      "category" : "Men Clothing",
      "cost": "25"
    },
    {
      "id": 3,
      "title": "Blue shirt",
      "category" : "Men Clothing",
      "cost": "22"
    },
    {
      "id": 4,
      "title": "Green shirt",
      "category" : "Men Clothing",
      "cost": "23"
    },
    {
      "id": 5,
      "title": "TV",
      "category": "Electronics",
      "cost": "33"
    },
    {
      "id": 6,
      "title": "toaster",
      "category": "Electronics",
      "cost": "38"
    },
    {
      "id": 7,
      "title": "projector",
      "category": "Electronics",
      "cost": "48"
    },
    {
      "id": 8,
      "title": "refrigerator",
      "category": "Electronics",
      "cost": "58"
    },
    {
       "id": 9,
      "title": "chain",
      "category": "Jewlary",
      "cost": "58"
    },
    {
       "id": 10,
      "title": "diamond",
      "category": "Jewlary",
      "cost": "65"
    },
    {
       "id": 11,
      "title": "gold",
      "category": "Jewlary",
      "cost": "69"
    },
    {
       "id": 12,
      "title": "silver",
      "category": "Jewlary",
      "cost": "70"
    }
  ]
}
